avh/__init__.py
avh/aliases.py
avh/auto_validate_by_history.py
avh/constraints/__init__.py
avh/constraints/_base.py
avh/constraints/_constraints.py
avh/constraints/_data_quality_program.py
avh/data_generation/__init__.py
avh/data_generation/_base.py
avh/data_generation/_categorical.py
avh/data_generation/_numeric.py
avh/data_generation/_pipeline.py
avh/data_issues/__init__.py
avh/data_issues/_base.py
avh/data_issues/_categorical.py
avh/data_issues/_dataset.py
avh/data_issues/_issues.py
avh/data_issues/_numeric.py
avh/metrics/__init__.py
avh/metrics/_base.py
avh/metrics/_categorical.py
avh/metrics/_metrics.py
avh/metrics/_numeric.py
avh/utility_functions.py
miautawn_auto_validate_by_history-0.3.0.dist-info/LICENSE
miautawn_auto_validate_by_history-0.3.0.dist-info/METADATA
miautawn_auto_validate_by_history-0.3.0.dist-info/WHEEL
miautawn_auto_validate_by_history-0.3.0.dist-info/RECORD
