Metadata-Version: 2.1
Name: miautawn-auto-validate-by-history
Version: 0.3.0
Summary: Automatic data quality validation for data pipelines
Home-page: https://github.com/Miautawn/Auto-Validate-By-History-Clone
Keywords: data,quality,pipeline
Author: miautawn
Author-email: miautawn@gmail.com
Requires-Python: >=3.10,<4.0
Classifier: Programming Language :: Python :: 3
Classifier: Programming Language :: Python :: 3.10
Classifier: Programming Language :: Python :: 3.11
Classifier: Programming Language :: Python :: 3.12
Requires-Dist: joblib (>=1.4.0,<2.0.0)
Requires-Dist: numpy (>=1.26.4,<2.0.0)
Requires-Dist: pandas (>=2.2.0,<3.0.0)
Requires-Dist: pyarrow (>=16.0.0,<17.0.0)
Requires-Dist: scikit-learn (>=1.4.2,<2.0.0)
Requires-Dist: statsmodels (>=0.14.1,<0.15.0)
Requires-Dist: tqdm (>=4.66.2,<5.0.0)
Project-URL: Repository, https://github.com/Miautawn/Auto-Validate-By-History-Clone
